[{"chartType":"7501","chartID":"7501-19900915","position":"1","lastW":"6","title":"THE JOKER","artist":"THE STEVE MILLER BAND","label":"CAPITOL","peak":"1","WoC":"6"},{"chartType":"7501","chartID":"7501-19900915","position":"2","lastW":"4","title":"GROOVE IS IN THE HEART/WHAT IS LOVE?","artist":"DEEE-LITE","label":"ELEKTRA","peak":"2","WoC":"5"},{"chartType":"7501","chartID":"7501-19900915","position":"3","lastW":"1","title":"ITSY BITSY TEENY WEENY YELLOW POLKA DOT BIKINI","artist":"BOMBALURINA","label":"CARPET","peak":"1","WoC":"8"},{"chartType":"7501","chartID":"7501-19900915","position":"4","lastW":"2","title":"FOUR BACHARACH AND DAVID SONGS (EP)","artist":"DEACON BLUE","label":"CBS","peak":"2","WoC":"4"},{"chartType":"7501","chartID":"7501-19900915","position":"5","lastW":"7","title":"WHAT TIME IS LOVE? FT THE CHILDREN OF THE REVOLUTION","artist":"KLF FEATURING THE CHILDREN OF THE REVOLUTION","label":"KLF COMMUNICATIONS","peak":"5","WoC":"6"},{"chartType":"7501","chartID":"7501-19900915","position":"6","lastW":"3","title":"WHERE ARE YOU BABY?","artist":"BETTY BOO","label":"RHYTHM KING","peak":"3","WoC":"6"},{"chartType":"7501","chartID":"7501-19900915","position":"7","lastW":"23","title":"THE SPACE JUNGLE","artist":"ADAMSKI","label":"MCA","peak":"7","WoC":"2"},{"chartType":"7501","chartID":"7501-19900915","position":"8","lastW":"5","title":"TONIGHT","artist":"NEW KIDS ON THE BLOCK","label":"CBS","peak":"3","WoC":"7"},{"chartType":"7501","chartID":"7501-19900915","position":"9","lastW":"14","title":"VISION OF LOVE","artist":"MARIAH CAREY","label":"CBS","peak":"9","WoC":"7"},{"chartType":"7501","chartID":"7501-19900915","position":"10","lastW":"9","title":"RHYTHM OF THE RAIN","artist":"JASON DONOVAN","label":"PWL","peak":"9","WoC":"3"},{"chartType":"7501","chartID":"7501-19900915","position":"11","lastW":"28","title":"GROOVY TRAIN","artist":"THE FARM","label":"PRODUCE","peak":"11","WoC":"3"},{"chartType":"7501","chartID":"7501-19900915","position":"12","lastW":"10","title":"PRAYING FOR TIME","artist":"GEORGE MICHAEL","label":"EPIC","peak":"6","WoC":"4"},{"chartType":"7501","chartID":"7501-19900915","position":"13","lastW":"21","title":"DON'T BE A FOOL","artist":"LOOSE ENDS","label":"10","peak":"13","WoC":"4"},{"chartType":"7501","chartID":"7501-19900915","position":"14","lastW":"29","title":"LIVIN' IN THE LIGHT","artist":"CARON WHEELER","label":"RCA","peak":"14","WoC":"2"},{"chartType":"7501","chartID":"7501-19900915","position":"15","lastW":"32","title":"BLACK CAT","artist":"JANET JACKSON","label":"A&M","peak":"15","WoC":"2"},{"chartType":"7501","chartID":"7501-19900915","position":"16","lastW":"New","title":"SUICIDE BLONDE","artist":"INXS","label":"MERCURY","peak":"16","WoC":"1"},{"chartType":"7501","chartID":"7501-19900915","position":"17","lastW":"8","title":"NAKED IN THE RAIN","artist":"BLUE PEARL","label":"BIG LIFE","peak":"4","WoC":"13"},{"chartType":"7501","chartID":"7501-19900915","position":"18","lastW":"19","title":"END OF THE WORLD","artist":"SONIA","label":"CHRYSALIS","peak":"18","WoC":"4"},{"chartType":"7501","chartID":"7501-19900915","position":"19","lastW":"12","title":"SILHOUETTES","artist":"CLIFF RICHARD","label":"EMI","peak":"10","WoC":"4"},{"chartType":"7501","chartID":"7501-19900915","position":"20","lastW":"13","title":"LISTEN TO YOUR HEART/DANGEROUS","artist":"ROXETTE","label":"EMI","peak":"6","WoC":"6"},{"chartType":"7501","chartID":"7501-19900915","position":"21","lastW":"11","title":"CAN CAN YOU PARTY","artist":"JIVE BUNNY AND THE MASTERMIXERS","label":"MUSIC FACTORY DANCE","peak":"8","WoC":"4"},{"chartType":"7501","chartID":"7501-19900915","position":"22","lastW":"38","title":"FASCINATING RHYTHM","artist":"BASS-O-MATIC","label":"VIRGIN","peak":"22","WoC":"3"},{"chartType":"7501","chartID":"7501-19900915","position":"23","lastW":"31","title":"LIFE'S WHAT YOU MAKE IT {1990}","artist":"TALK TALK","label":"PARLOPHONE","peak":"23","WoC":"3"},{"chartType":"7501","chartID":"7501-19900915","position":"24","lastW":"17","title":"I'M FREE FT JUNIOR REID","artist":"SOUP DRAGONS FEATURING JUNIOR REID","label":"RAW","peak":"5","WoC":"10"},{"chartType":"7501","chartID":"7501-19900915","position":"25","lastW":"15","title":"TOM'S DINER FT SUZANNE VEGA","artist":"DNA FEATURING SUZANNE VEGA","label":"A&M","peak":"2","WoC":"8"},{"chartType":"7501","chartID":"7501-19900915","position":"26","lastW":"New","title":"SHOW ME HEAVEN","artist":"MARIA MCKEE","label":"EPIC","peak":"26","WoC":"1"},{"chartType":"7501","chartID":"7501-19900915","position":"27","lastW":"45","title":"I'VE BEEN THINKING ABOUT YOU","artist":"LONDONBEAT","label":"ANXIOUS","peak":"27","WoC":"3"},{"chartType":"7501","chartID":"7501-19900915","position":"28","lastW":"20","title":"KING OF WISHFUL THINKING","artist":"GO WEST","label":"CHRYSALIS","peak":"18","WoC":"8"},{"chartType":"7501","chartID":"7501-19900915","position":"29","lastW":"35","title":"EPIC {1990 RE-RELEASE}","artist":"FAITH NO MORE","label":"SLASH","peak":"29","WoC":"2"},{"chartType":"7501","chartID":"7501-19900915","position":"30","lastW":"16","title":"TURTLE POWER","artist":"PARTNERS IN KRYME","label":"SBK","peak":"1","WoC":"9"},{"chartType":"7501","chartID":"7501-19900915","position":"31","lastW":"22","title":"BLAZE OF GLORY","artist":"JON BON JOVI","label":"VERTIGO","peak":"13","WoC":"7"},{"chartType":"7501","chartID":"7501-19900915","position":"32","lastW":"Re","title":"FOOL'S GOLD/WHAT THE WORLD IS WAITING FOR","artist":"THE STONE ROSES","label":"SILVERTONE","peak":"8","WoC":"15"},{"chartType":"7501","chartID":"7501-19900915","position":"33","lastW":"18","title":"U CAN'T TOUCH THIS","artist":"MC HAMMER","label":"CAPITOL","peak":"3","WoC":"15"},{"chartType":"7501","chartID":"7501-19900915","position":"34","lastW":"24","title":"NEXT TO YOU","artist":"ASWAD","label":"MANGO","peak":"24","WoC":"5"},{"chartType":"7501","chartID":"7501-19900915","position":"35","lastW":"36","title":"LA SERENISSIMA","artist":"DNA","label":"RAW BASS","peak":"35","WoC":"5"},{"chartType":"7501","chartID":"7501-19900915","position":"36","lastW":"25","title":"SILLY GAMES FT JANET KAY","artist":"LINDY LAYTON FEATURING JANET KAY","label":"ARISTA","peak":"22","WoC":"6"},{"chartType":"7501","chartID":"7501-19900915","position":"37","lastW":"51","title":"THERE SHE GOES AGAIN/MISLED","artist":"QUIREBOYS","label":"PARLOPHONE","peak":"37","WoC":"2"},{"chartType":"7501","chartID":"7501-19900915","position":"38","lastW":"39","title":"ICEBLINK LUCK","artist":"COCTEAU TWINS","label":"4AD","peak":"38","WoC":"2"},{"chartType":"7501","chartID":"7501-19900915","position":"39","lastW":"34","title":"GET ME OUT","artist":"NEW MODEL ARMY","label":"EMI","peak":"34","WoC":"2"},{"chartType":"7501","chartID":"7501-19900915","position":"40","lastW":"New","title":"NOTHING TO LOSE","artist":"S-EXPRESS","label":"RHYTHM KING","peak":"40","WoC":"1"},{"chartType":"7501","chartID":"7501-19900915","position":"41","lastW":"41","title":"PEACE THROUGHOUT THE WORLD FT JAZZIE B","artist":"MAXI PRIEST FEATURING JAZZIE B","label":"10","peak":"41","WoC":"3"},{"chartType":"7501","chartID":"7501-19900915","position":"42","lastW":"30","title":"COME TOGETHER","artist":"PRIMAL SCREAM","label":"CREATION","peak":"26","WoC":"5"},{"chartType":"7501","chartID":"7501-19900915","position":"43","lastW":"26","title":"HARDCORE UPROAR","artist":"TOGETHER","label":"FFRR","peak":"12","WoC":"7"},{"chartType":"7501","chartID":"7501-19900915","position":"44","lastW":"New","title":"TUNES SPLITS THE ATOM","artist":"MC TUNES VS 808 STATE","label":"ZTT","peak":"44","WoC":"1"},{"chartType":"7501","chartID":"7501-19900915","position":"45","lastW":"52","title":"LOVER/MONEY","artist":"DAN REED NETWORK","label":"MERCURY","peak":"45","WoC":"2"},{"chartType":"7501","chartID":"7501-19900915","position":"46","lastW":"27","title":"ENGLISHMAN IN NEW YORK","artist":"STING","label":"A&M","peak":"15","WoC":"6"},{"chartType":"7501","chartID":"7501-19900915","position":"47","lastW":"40","title":"RELEASE ME","artist":"WILSON PHILLIPS","label":"SBK","peak":"36","WoC":"5"},{"chartType":"7501","chartID":"7501-19900915","position":"48","lastW":"55","title":"HARD TO HANDLE","artist":"THE BLACK CROWES","label":"DEF AMERICAN","peak":"48","WoC":"3"},{"chartType":"7501","chartID":"7501-19900915","position":"49","lastW":"54","title":"HEY VENUS","artist":"THAT PETROL EMOTION","label":"VIRGIN","peak":"49","WoC":"3"},{"chartType":"7501","chartID":"7501-19900915","position":"50","lastW":"58","title":"WOW WOW - NA NA","artist":"GRAND PLAZ","label":"URBAN","peak":"50","WoC":"2"},{"chartType":"7501","chartID":"7501-19900915","position":"51","lastW":"46","title":"ROLLERCOASTER","artist":"THE JESUS AND MARY CHAIN","label":"BLANCO","peak":"46","WoC":"2"},{"chartType":"7501","chartID":"7501-19900915","position":"52","lastW":"37","title":"HANKY PANKY","artist":"MADONNA","label":"SIRE","peak":"2","WoC":"9"},{"chartType":"7501","chartID":"7501-19900915","position":"53","lastW":"33","title":"NOW YOU'RE GONE","artist":"WHITESNAKE","label":"EMI","peak":"31","WoC":"4"},{"chartType":"7501","chartID":"7501-19900915","position":"54","lastW":"59","title":"HIGHER GROUND {1990 RE-RELEASE}","artist":"RED HOT CHILI PEPPERS","label":"EMI-USA","peak":"54","WoC":"2"},{"chartType":"7501","chartID":"7501-19900915","position":"55","lastW":"64","title":"HARD UP","artist":"AWESOME 3","label":"A&M","peak":"55","WoC":"2"},{"chartType":"7501","chartID":"7501-19900915","position":"56","lastW":"New","title":"BURUNDI BLUES","artist":"BEATS INTERNATIONAL","label":"GO! BEAT","peak":"56","WoC":"1"},{"chartType":"7501","chartID":"7501-19900915","position":"57","lastW":"New","title":"TIMELESS MELODY","artist":"THE LA'S","label":"GO! DISCS","peak":"57","WoC":"1"},{"chartType":"7501","chartID":"7501-19900915","position":"58","lastW":"76","title":"COMING BACK FOR MORE","artist":"LA MIX","label":"A&M","peak":"58","WoC":"2"},{"chartType":"7501","chartID":"7501-19900915","position":"59","lastW":"42","title":"LOOK ME IN THE HEART","artist":"TINA TURNER","label":"CAPITOL","peak":"31","WoC":"6"},{"chartType":"7501","chartID":"7501-19900915","position":"60","lastW":"43","title":"HEART LIKE A WHEEL","artist":"THE HUMAN LEAGUE","label":"VIRGIN","peak":"29","WoC":"5"},{"chartType":"7501","chartID":"7501-19900915","position":"61","lastW":"48","title":"SACRIFICE/HEALING HANDS","artist":"ELTON JOHN","label":"ROCKET","peak":"1","WoC":"15"},{"chartType":"7501","chartID":"7501-19900915","position":"62","lastW":"New","title":"SUNRISE FT CARROLL THOMPSON","artist":"MOVEMENT 98 FEATURING CARROLL THOMPSON","label":"CIRCA","peak":"62","WoC":"1"},{"chartType":"7501","chartID":"7501-19900915","position":"63","lastW":"New","title":"EMPTY WORLD","artist":"DOGS D'AMOUR","label":"CHINA","peak":"63","WoC":"1"},{"chartType":"7501","chartID":"7501-19900915","position":"64","lastW":"56","title":"WHITE LIGHTNING","artist":"THE FALL","label":"COG SINISTER","peak":"56","WoC":"2"},{"chartType":"7501","chartID":"7501-19900915","position":"65","lastW":"47","title":"LFO","artist":"LFO","label":"WARP","peak":"12","WoC":"10"},{"chartType":"7501","chartID":"7501-19900915","position":"66","lastW":"82","title":"WAY DOWN NOW","artist":"WORLD PARTY","label":"ENSIGN","peak":"66","WoC":"3"},{"chartType":"7501","chartID":"7501-19900915","position":"67","lastW":"77","title":"SUMMER IN SIAM","artist":"THE POGUES","label":"PM","peak":"67","WoC":"2"},{"chartType":"7501","chartID":"7501-19900915","position":"68","lastW":"50","title":"THE RIGHT COMBINATION","artist":"SEIKO AND DONNIE","label":"EPIC","peak":"44","WoC":"5"},{"chartType":"7501","chartID":"7501-19900915","position":"69","lastW":"61","title":"UP AND DOWN","artist":"HIGH","label":"LONDON","peak":"53","WoC":"4"},{"chartType":"7501","chartID":"7501-19900915","position":"70","lastW":"44","title":"TRICKY DISCO","artist":"TRICKY DISCO","label":"WARP","peak":"14","WoC":"8"},{"chartType":"7501","chartID":"7501-19900915","position":"71","lastW":"New","title":"YOU DON'T LOVE ME","artist":"JAGGED EDGE","label":"POLYDOR","peak":"71","WoC":"1"},{"chartType":"7501","chartID":"7501-19900915","position":"72","lastW":"80","title":"GREENBANK DRIVE","artist":"THE CHRISTIANS","label":"ISLAND","peak":"72","WoC":"2"},{"chartType":"7501","chartID":"7501-19900915","position":"73","lastW":"75","title":"ONLY ONE WORD","artist":"PROPAGANDA","label":"VIRGIN","peak":"73","WoC":"4"},{"chartType":"7501","chartID":"7501-19900915","position":"74","lastW":"New","title":"PAIN KILLER","artist":"JUDAS PRIEST","label":"CBS","peak":"74","WoC":"1"},{"chartType":"7501","chartID":"7501-19900915","position":"75","lastW":"60","title":"WALKING BY MYSELF","artist":"GARY MOORE","label":"VIRGIN","peak":"48","WoC":"5"},{"chartType":"7501","chartID":"7501-19900915","position":"76","lastW":"74","title":"DANCE DANCE","artist":"DESKEE","label":"BIG ONE","peak":"74","WoC":"2"},{"chartType":"7501","chartID":"7501-19900915","position":"77","lastW":"66","title":"HEAVEN KNOWS","artist":"LALAH HATHAWAY","label":"VIRGIN AMERICA","peak":"66","WoC":"4"},{"chartType":"7501","chartID":"7501-19900915","position":"78","lastW":"New","title":"ANOTHER SLEEPLESS NIGHT","artist":"MIKE 'HITMAN' WILSON","label":"ARISTA","peak":"78","WoC":"1"},{"chartType":"7501","chartID":"7501-19900915","position":"79","lastW":"New","title":"DANCE","artist":"EARTH PEOPLE","label":"NO-LABEL","peak":"79","WoC":"1"},{"chartType":"7501","chartID":"7501-19900915","position":"80","lastW":"New","title":"BAREFOOT IN THE HEAD","artist":"A MAN CALLED ADAM","label":"BIG LIFE","peak":"80","WoC":"1"},{"chartType":"7501","chartID":"7501-19900915","position":"81","lastW":"New","title":"KOOL THING","artist":"SONIC YOUTH","label":"NO-LABEL","peak":"81","WoC":"1"},{"chartType":"7501","chartID":"7501-19900915","position":"82","lastW":"New","title":"HEADLIGHTS ON THE PARADE","artist":"BLUE NILE","label":"LINN","peak":"82","WoC":"1"},{"chartType":"7501","chartID":"7501-19900915","position":"83","lastW":"85","title":"CLASS ROCK","artist":"TACK HEAD","label":"NO-LABEL","peak":"83","WoC":"2"},{"chartType":"7501","chartID":"7501-19900915","position":"84","lastW":"87","title":"THE BOOMIN' SYSTEM FT UNCLE L","artist":"LL COOL J FEATURING UNCLE L","label":"NO-LABEL","peak":"83","WoC":"3"},{"chartType":"7501","chartID":"7501-19900915","position":"85","lastW":"99","title":"STEP ON","artist":"HAPPY MONDAYS","label":"FACTORY","peak":"5","WoC":"20"},{"chartType":"7501","chartID":"7501-19900915","position":"86","lastW":"93","title":"LACE VIRGINIA","artist":"AN EMOTIONAL FISH","label":"NO-LABEL","peak":"86","WoC":"2"},{"chartType":"7501","chartID":"7501-19900915","position":"87","lastW":"81","title":"TYPE","artist":"LIVING COLOUR","label":"EPIC","peak":"77","WoC":"3"},{"chartType":"7501","chartID":"7501-19900915","position":"88","lastW":"New","title":"SAY HELLO","artist":"BREATHE","label":"NO-LABEL","peak":"88","WoC":"1"},{"chartType":"7501","chartID":"7501-19900915","position":"89","lastW":"New","title":"WONDERFUL WORLD","artist":"WILDSKI","label":"NO-LABEL","peak":"89","WoC":"1"},{"chartType":"7501","chartID":"7501-19900915","position":"90","lastW":"90","title":"GANG BANG","artist":"BLACK LACE","label":"NO-LABEL","peak":"90","WoC":"2"},{"chartType":"7501","chartID":"7501-19900915","position":"91","lastW":"New","title":"JUSTICE IN ONTARIO","artist":"STEVE EARLE AND THE DUKES","label":"NO-LABEL","peak":"91","WoC":"1"},{"chartType":"7501","chartID":"7501-19900915","position":"92","lastW":"86","title":"CRYSTAL CLEAR","artist":"THE DARLING BUDS","label":"NO-LABEL","peak":"85","WoC":"3"},{"chartType":"7501","chartID":"7501-19900915","position":"93","lastW":"94","title":"DO YOU REALLY WANT MY LOVE?","artist":"MELBA MOORE","label":"NO-LABEL","peak":"93","WoC":"2"},{"chartType":"7501","chartID":"7501-19900915","position":"94","lastW":"Re","title":"NESSUN DORMA","artist":"LUCIANO PAVAROTTI","label":"DECCA","peak":"2","WoC":"12"},{"chartType":"7501","chartID":"7501-19900915","position":"95","lastW":"97","title":"I NEED RHYTHM","artist":"SPLASH","label":"NO-LABEL","peak":"88","WoC":"3"},{"chartType":"7501","chartID":"7501-19900915","position":"96","lastW":"88","title":"CREATURES FROM THE BLACK LEATHER LAGOON","artist":"CRAMPS","label":"NO-LABEL","peak":"88","WoC":"3"},{"chartType":"7501","chartID":"7501-19900915","position":"97","lastW":"96","title":"FIRE TO ICE","artist":"ASSOCIATES","label":"NO-LABEL","peak":"92","WoC":"3"},{"chartType":"7501","chartID":"7501-19900915","position":"98","lastW":"98","title":"LIFE","artist":"DAVID GRANT AND ORIGINAL DOUBLE T","label":"NO-LABEL","peak":"98","WoC":"2"},{"chartType":"7501","chartID":"7501-19900915","position":"99","lastW":"New","title":"RING MY BELL {1990}","artist":"ANITA WARD","label":"NO-LABEL","peak":"99","WoC":"1"},{"chartType":"7501","chartID":"7501-19900915","position":"100","lastW":"Re","title":"MADCHESTER RAVE ON (EP)","artist":"HAPPY MONDAYS","label":"FACTORY","peak":"19","WoC":"24"}]