[{"chartType":"7501","chartID":"7501-20000610","position":"1","lastW":"1","title":"IT FEELS SO GOOD","artist":"SONIQUE","label":"UNIVERSAL","peak":"1","WoC":"2"},{"chartType":"7501","chartID":"7501-20000610","position":"2","lastW":"2","title":"REACH","artist":"S CLUB 7","label":"POLYDOR","peak":"2","WoC":"2"},{"chartType":"7501","chartID":"7501-20000610","position":"3","lastW":"New","title":"NEW BEGINNING/BRIGHT EYES","artist":"STEPHEN GATELY","label":"A&M","peak":"3","WoC":"1"},{"chartType":"7501","chartID":"7501-20000610","position":"4","lastW":"New","title":"ON THE BEACH","artist":"YORK","label":"MANIFESTO","peak":"4","WoC":"1"},{"chartType":"7501","chartID":"7501-20000610","position":"5","lastW":"New","title":"SHACKLES (PRAISE YOU)","artist":"MARY MARY","label":"COLUMBIA","peak":"5","WoC":"1"},{"chartType":"7501","chartID":"7501-20000610","position":"6","lastW":"New","title":"THERE YOU GO","artist":"PINK","label":"LAFACE","peak":"6","WoC":"1"},{"chartType":"7501","chartID":"7501-20000610","position":"7","lastW":"New","title":"FORGOT ABOUT DRE","artist":"DR DRE FT EMINEM","label":"INTERSCOPE","peak":"7","WoC":"1"},{"chartType":"7501","chartID":"7501-20000610","position":"8","lastW":"3","title":"IT'S MY LIFE","artist":"BON JOVI","label":"MERCURY","peak":"3","WoC":"2"},{"chartType":"7501","chartID":"7501-20000610","position":"9","lastW":"6","title":"OOPS! I DID IT AGAIN","artist":"BRITNEY SPEARS","label":"JIVE","peak":"1","WoC":"5"},{"chartType":"7501","chartID":"7501-20000610","position":"10","lastW":"5","title":"DON'T CALL ME BABY","artist":"MADISON AVENUE","label":"VC RECORDINGS","peak":"1","WoC":"4"},{"chartType":"7501","chartID":"7501-20000610","position":"11","lastW":"4","title":"DAY & NIGHT","artist":"BILLIE PIPER","label":"INNOCENT","peak":"1","WoC":"3"},{"chartType":"7501","chartID":"7501-20000610","position":"12","lastW":"New","title":"HANDS UP","artist":"TREVOR & SIMON","label":"SUBSTANCE","peak":"12","WoC":"1"},{"chartType":"7501","chartID":"7501-20000610","position":"13","lastW":"New","title":"YOU'RE MY ANGEL","artist":"MIKEY GRAHAM","label":"PUBLIC","peak":"13","WoC":"1"},{"chartType":"7501","chartID":"7501-20000610","position":"14","lastW":"7","title":"SEX BOMB","artist":"TOM JONES & MOUSSE T","label":"GUT","peak":"3","WoC":"4"},{"chartType":"7501","chartID":"7501-20000610","position":"15","lastW":"9","title":"THE BAD TOUCH","artist":"BLOODHOUND GANG","label":"GEFFEN","peak":"4","WoC":"9"},{"chartType":"7501","chartID":"7501-20000610","position":"16","lastW":"8","title":"MASTERBLASTER 2000","artist":"DJ LUCK & MC NEAT","label":"RED ROSE","peak":"5","WoC":"3"},{"chartType":"7501","chartID":"7501-20000610","position":"17","lastW":"New","title":"WE'RE REALLY SAYING SOMETHING","artist":"BUFFALO G","label":"EPIC","peak":"17","WoC":"1"},{"chartType":"7501","chartID":"7501-20000610","position":"18","lastW":"10","title":"TAKEN FOR GRANTED","artist":"SIA","label":"LONG LOST BROTHER","peak":"10","WoC":"2"},{"chartType":"7501","chartID":"7501-20000610","position":"19","lastW":"16","title":"THONG SONG","artist":"SISQO","label":"DEF SOUL","peak":"3","WoC":"8"},{"chartType":"7501","chartID":"7501-20000610","position":"20","lastW":"12","title":"HEART OF ASIA","artist":"WATERGATE","label":"POSITIVA","peak":"3","WoC":"5"},{"chartType":"7501","chartID":"7501-20000610","position":"21","lastW":"26","title":"AMAZED","artist":"LONESTAR","label":"BNA/GRAPEVINE","peak":"21","WoC":"9"},{"chartType":"7501","chartID":"7501-20000610","position":"22","lastW":"13","title":"BOUND 4 DA RELOAD (CASUALTY)","artist":"OXIDE & NEUTRINO","label":"EAST WEST","peak":"1","WoC":"6"},{"chartType":"7501","chartID":"7501-20000610","position":"23","lastW":"14","title":"LUVSTRUCK","artist":"SOUTHSIDE SPINNERS","label":"AM:PM","peak":"9","WoC":"3"},{"chartType":"7501","chartID":"7501-20000610","position":"24","lastW":"17","title":"TOCA'S MIRACLE","artist":"COCO vs FRAGMA","label":"POSITIVA","peak":"1","WoC":"8"},{"chartType":"7501","chartID":"7501-20000610","position":"25","lastW":"11","title":"I DON'T SMOKE","artist":"DJ DEE KLINE","label":"EAST WEST","peak":"11","WoC":"2"},{"chartType":"7501","chartID":"7501-20000610","position":"26","lastW":"New","title":"AROUND THE WORLD","artist":"AQUA","label":"UNIVERSAL","peak":"26","WoC":"1"},{"chartType":"7501","chartID":"7501-20000610","position":"27","lastW":"20","title":"FILL ME IN","artist":"CRAIG DAVID","label":"WILDSTAR","peak":"1","WoC":"9"},{"chartType":"7501","chartID":"7501-20000610","position":"28","lastW":"New","title":"CRYPTIK SOULS CREW","artist":"LEN","label":"COLUMBIA","peak":"28","WoC":"1"},{"chartType":"7501","chartID":"7501-20000610","position":"29","lastW":"New","title":"SAVE ME","artist":"EMBRACE","label":"HUT","peak":"29","WoC":"1"},{"chartType":"7501","chartID":"7501-20000610","position":"30","lastW":"21","title":"HE WASN'T MAN ENOUGH","artist":"TONI BRAXTON","label":"ARISTA","peak":"5","WoC":"7"},{"chartType":"7501","chartID":"7501-20000610","position":"31","lastW":"18","title":"KOOCHY","artist":"ARMAND VAN HELDEN","label":"FFRR","peak":"4","WoC":"4"},{"chartType":"7501","chartID":"7501-20000610","position":"32","lastW":"New","title":"CATCH THE SUN","artist":"DOVES","label":"HEAVENLY","peak":"32","WoC":"1"},{"chartType":"7501","chartID":"7501-20000610","position":"33","lastW":"New","title":"CARMEN QUEASY","artist":"MAXIM","label":"XL RECORDINGS","peak":"33","WoC":"1"},{"chartType":"7501","chartID":"7501-20000610","position":"34","lastW":"22","title":"ACHILLES HEEL","artist":"TOPLOADER","label":"SONY S2","peak":"8","WoC":"5"},{"chartType":"7501","chartID":"7501-20000610","position":"35","lastW":"24","title":"MAMBO ITALIANO","artist":"SHAFT","label":"WONDERBOY","peak":"12","WoC":"4"},{"chartType":"7501","chartID":"7501-20000610","position":"36","lastW":"15","title":"LEGAL MAN","artist":"BELLE & SEBASTIAN","label":"JEEPSTER","peak":"15","WoC":"2"},{"chartType":"7501","chartID":"7501-20000610","position":"37","lastW":"23","title":"TELL ME WHY (THE RIDDLE)","artist":"PAUL VAN DYK FT SAINT ETIENNE","label":"DEVIANT","peak":"7","WoC":"4"},{"chartType":"7501","chartID":"7501-20000610","position":"38","lastW":"New","title":"GET OFF","artist":"DANDY WARHOLS","label":"CAPITOL","peak":"38","WoC":"1"},{"chartType":"7501","chartID":"7501-20000610","position":"39","lastW":"27","title":"FLOWERS","artist":"SWEET FEMALE ATTITUDE","label":"WEA","peak":"2","WoC":"9"},{"chartType":"7501","chartID":"7501-20000610","position":"40","lastW":"29","title":"PRIVATE EMOTION","artist":"RICKY MARTIN FT MEJA","label":"COLUMBIA","peak":"9","WoC":"7"},{"chartType":"7501","chartID":"7501-20000610","position":"41","lastW":"28","title":"WALKING ON WATER","artist":"MADASUN","label":"V2","peak":"14","WoC":"3"},{"chartType":"7501","chartID":"7501-20000610","position":"42","lastW":"38","title":"NEVER BE THE SAME AGAIN","artist":"MELANIE C/LISA LEFT EYE LOPES","label":"VIRGIN","peak":"1","WoC":"11"},{"chartType":"7501","chartID":"7501-20000610","position":"43","lastW":"19","title":"PUMPIN","artist":"NOVY VS ENIAC","label":"POSITIVA","peak":"19","WoC":"2"},{"chartType":"7501","chartID":"7501-20000610","position":"44","lastW":"42","title":"CANDY","artist":"MANDY MOORE","label":"EPIC","peak":"6","WoC":"6"},{"chartType":"7501","chartID":"7501-20000610","position":"45","lastW":"34","title":"PROUD","artist":"HEATHER SMALL","label":"ARISTA","peak":"16","WoC":"4"},{"chartType":"7501","chartID":"7501-20000610","position":"46","lastW":"35","title":"BLOW YA MIND","artist":"LOCK 'N' LOAD","label":"PEPPER","peak":"6","WoC":"10"},{"chartType":"7501","chartID":"7501-20000610","position":"47","lastW":"31","title":"CRAZY LOVE","artist":"MJ COLE","label":"TALKIN LOUD","peak":"10","WoC":"6"},{"chartType":"7501","chartID":"7501-20000610","position":"48","lastW":"37","title":"BUGGIN' ME","artist":"TRUE STEPPERS FT DANE BOWERS","label":"NULIFE","peak":"6","WoC":"7"},{"chartType":"7501","chartID":"7501-20000610","position":"49","lastW":"New","title":"SACRED CYCLES","artist":"PETER LAZONBY","label":"HOOJ CHOONS","peak":"49","WoC":"1"},{"chartType":"7501","chartID":"7501-20000610","position":"50","lastW":"25","title":"MAKE ME BAD","artist":"KORN","label":"EPIC","peak":"25","WoC":"2"},{"chartType":"7501","chartID":"7501-20000610","position":"51","lastW":"64","title":"SHOW ME THE MEANING OF BEING LONELY","artist":"BACKSTREET BOYS","label":"JIVE","peak":"3","WoC":"18"},{"chartType":"7501","chartID":"7501-20000610","position":"52","lastW":"41","title":"SAY MY NAME","artist":"DESTINY'S CHILD","label":"COLUMBIA","peak":"3","WoC":"10"},{"chartType":"7501","chartID":"7501-20000610","position":"53","lastW":"New","title":"SOMEONE ELSE NOT ME","artist":"DURAN DURAN","label":"HOLLYWOOD","peak":"53","WoC":"1"},{"chartType":"7501","chartID":"7501-20000610","position":"54","lastW":"52","title":"YOU SEE THE TROUBLE WITH","artist":"BLACK LEGEND","label":"RISE","peak":"48","WoC":"6"},{"chartType":"7501","chartID":"7501-20000610","position":"55","lastW":"56","title":"I WANNA LOVE YOU FOREVER","artist":"JESSICA SIMPSON","label":"COLUMBIA","peak":"7","WoC":"8"},{"chartType":"7501","chartID":"7501-20000610","position":"56","lastW":"36","title":"IMPOSSIBLE","artist":"CHARLATANS","label":"UNIVERSAL","peak":"15","WoC":"3"},{"chartType":"7501","chartID":"7501-20000610","position":"57","lastW":"30","title":"THE WICKER MAN","artist":"IRON MAIDEN","label":"EMI","peak":"9","WoC":"4"},{"chartType":"7501","chartID":"7501-20000610","position":"58","lastW":"New","title":"THE RETURN (TIME TO SAY GOODBYE)","artist":"DJ VISAGE FT CLARISSA","label":"ONE STEP MUSIC","peak":"58","WoC":"1"},{"chartType":"7501","chartID":"7501-20000610","position":"59","lastW":"33","title":"SUMMER MOVED ON","artist":"A-HA","label":"WEA","peak":"33","WoC":"2"},{"chartType":"7501","chartID":"7501-20000610","position":"60","lastW":"48","title":"DEEPER SHADE OF BLUE","artist":"STEPS","label":"JIVE","peak":"4","WoC":"9"},{"chartType":"7501","chartID":"7501-20000610","position":"61","lastW":"60","title":"FOOL AGAIN","artist":"WESTLIFE","label":"RCA","peak":"1","WoC":"10"},{"chartType":"7501","chartID":"7501-20000610","position":"62","lastW":"New","title":"THE YOUNG MC","artist":"SUPERFUNK","label":"VIRGIN","peak":"62","WoC":"1"},{"chartType":"7501","chartID":"7501-20000610","position":"63","lastW":"New","title":"EASY","artist":"EMILIANA TORRINI","label":"ONE LITTLE INDIAN","peak":"63","WoC":"1"},{"chartType":"7501","chartID":"7501-20000610","position":"64","lastW":"77","title":"MOVIN TOO FAST","artist":"ARTFUL DODGER & ROMINA JOHNSON","label":"LOCKED ON","peak":"2","WoC":"13"},{"chartType":"7501","chartID":"7501-20000610","position":"65","lastW":"72","title":"DON'T GIVE UP","artist":"CHICANE FT BRYAN ADAMS","label":"XTRAVAGANZA","peak":"1","WoC":"13"},{"chartType":"7501","chartID":"7501-20000610","position":"66","lastW":"55","title":"A SONG FOR THE LOVERS","artist":"RICHARD ASHCROFT","label":"HUT","peak":"3","WoC":"9"},{"chartType":"7501","chartID":"7501-20000610","position":"67","lastW":"New","title":"DESIRE","artist":"DJ ERIC","label":"DISTINCTIVE","peak":"67","WoC":"1"},{"chartType":"7501","chartID":"7501-20000610","position":"68","lastW":"32","title":"KID 2000","artist":"HYBRID FT CHRISSIE HYNDE","label":"VIRGIN/EMI","peak":"32","WoC":"2"},{"chartType":"7501","chartID":"7501-20000610","position":"69","lastW":"74","title":"PURE SHORES","artist":"ALL SAINTS","label":"LONDON","peak":"1","WoC":"16"},{"chartType":"7501","chartID":"7501-20000610","position":"70","lastW":"70","title":"PER SEMPRE AMORE (FOREVER IN LOVE)","artist":"LOLLY","label":"POLYDOR","peak":"11","WoC":"6"},{"chartType":"7501","chartID":"7501-20000610","position":"71","lastW":"47","title":"DIRTY WATER","artist":"MADE IN LONDON","label":"RCA","peak":"15","WoC":"5"},{"chartType":"7501","chartID":"7501-20000610","position":"72","lastW":"New","title":"FEEL SO GOOD","artist":"JON THE DENTIST VS OLLIE JAYE","label":"TIDY TRAX","peak":"72","WoC":"1"},{"chartType":"7501","chartID":"7501-20000610","position":"73","lastW":"53","title":"WHO FEELS LOVE?","artist":"OASIS","label":"BIG BROTHER","peak":"4","WoC":"7"},{"chartType":"7501","chartID":"7501-20000610","position":"74","lastW":"81","title":"THE FIRST TIME EVER I SAW YOUR FACE","artist":"CELINE DION","label":"EPIC","peak":"19","WoC":"8"},{"chartType":"7501","chartID":"7501-20000610","position":"75","lastW":"New","title":"LOVE BUG","artist":"RAMSEY & FEN FT LYNSEY MOORE","label":"NEBULA","peak":"75","WoC":"1"},{"chartType":"7501","chartID":"7501-20000610","position":"76","lastW":"78","title":"AMERICAN PIE","artist":"MADONNA","label":"MAVERICK","peak":"1","WoC":"14"},{"chartType":"7501","chartID":"7501-20000610","position":"77","lastW":"71","title":"BAG IT UP","artist":"GERI HALLIWELL","label":"EMI","peak":"1","WoC":"12"},{"chartType":"7501","chartID":"7501-20000610","position":"78","lastW":"New","title":"THE CRYSTAL LAKE","artist":"GRANDADDY","label":"V2","peak":"78","WoC":"1"},{"chartType":"7501","chartID":"7501-20000610","position":"79","lastW":"40","title":"DON'T WANNA LET YOU GO","artist":"FIVE","label":"RCA","peak":"9","WoC":"13"},{"chartType":"7501","chartID":"7501-20000610","position":"80","lastW":"New","title":"LET ME GET ON TOP","artist":"BASS JUMPERS","label":"PEPPER","peak":"80","WoC":"1"},{"chartType":"7501","chartID":"7501-20000610","position":"81","lastW":"39","title":"WHAT'S YOUR NAME?","artist":"ANGEL LEE","label":"WEA","peak":"39","WoC":"2"},{"chartType":"7501","chartID":"7501-20000610","position":"82","lastW":"80","title":"THE BEST IS YET TO COME","artist":"SCOOCH","label":"ACCOLADE","peak":"12","WoC":"6"},{"chartType":"7501","chartID":"7501-20000610","position":"83","lastW":"88","title":"RISE","artist":"GABRIELLE","label":"GO BEAT","peak":"1","WoC":"17"},{"chartType":"7501","chartID":"7501-20000610","position":"84","lastW":"75","title":"THE TIME IS NOW","artist":"MOLOKO","label":"ECHO","peak":"2","WoC":"11"},{"chartType":"7501","chartID":"7501-20000610","position":"85","lastW":"Re","title":"SITTING DOWN HERE","artist":"LENE MARLIN","label":"VIRGIN","peak":"5","WoC":"12"},{"chartType":"7501","chartID":"7501-20000610","position":"86","lastW":"46","title":"ARSENAL NUMBER ONE/OUR GOAL","artist":"ARSENAL F.C.","label":"GRAPEVINE","peak":"46","WoC":"2"},{"chartType":"7501","chartID":"7501-20000610","position":"87","lastW":"Re","title":"KILLER","artist":"ATB","label":"SOUND OF MINISTRY","peak":"4","WoC":"9"},{"chartType":"7501","chartID":"7501-20000610","position":"88","lastW":"New","title":"I GET LIVE","artist":"MIKE & CHARLIE","label":"REGAL RECORDINGS","peak":"88","WoC":"1"},{"chartType":"7501","chartID":"7501-20000610","position":"89","lastW":"45","title":"WHAT'S GOING ON","artist":"WOOKIE","label":"S2S","peak":"45","WoC":"2"},{"chartType":"7501","chartID":"7501-20000610","position":"90","lastW":"Re","title":"AFTER THE RAIN HAS FALLEN","artist":"STING","label":"A&M","peak":"31","WoC":"5"},{"chartType":"7501","chartID":"7501-20000610","position":"91","lastW":"Re","title":"SEE YA","artist":"ATOMIC KITTEN","label":"INNOCENT","peak":"6","WoC":"7"},{"chartType":"7501","chartID":"7501-20000610","position":"92","lastW":"92","title":"BYE BYE BYE","artist":"NSYNC","label":"JIVE","peak":"3","WoC":"10"},{"chartType":"7501","chartID":"7501-20000610","position":"93","lastW":"Re","title":"LIGHT A CANDLE","artist":"DANIEL O'DONNELL","label":"RITZ","peak":"23","WoC":"7"},{"chartType":"7501","chartID":"7501-20000610","position":"94","lastW":"51","title":"LETTING THE CABLES SLEEP","artist":"BUSH","label":"TRAUMA/POLYDOR","peak":"51","WoC":"2"},{"chartType":"7501","chartID":"7501-20000610","position":"95","lastW":"Re","title":"CRASH AND BURN","artist":"SAVAGE GARDEN","label":"COLUMBIA","peak":"14","WoC":"7"},{"chartType":"7501","chartID":"7501-20000610","position":"96","lastW":"49","title":"NEW WAY, NEW LIFE","artist":"ASIAN DUB FOUNDATION","label":"FFRR","peak":"49","WoC":"2"},{"chartType":"7501","chartID":"7501-20000610","position":"97","lastW":"Re","title":"BINGO BANGO","artist":"BASEMENT JAXX","label":"XL RECORDINGS","peak":"13","WoC":"5"},{"chartType":"7501","chartID":"7501-20000610","position":"98","lastW":"93","title":"VIVRANT THING","artist":"Q-TIP","label":"ARISTA","peak":"39","WoC":"4"},{"chartType":"7501","chartID":"7501-20000610","position":"99","lastW":"New","title":"HARD BEAT EP 13","artist":"VARIOUS ARTISTS","label":"NUKLEUZ","peak":"99","WoC":"1"},{"chartType":"7501","chartID":"7501-20000610","position":"100","lastW":"59","title":"AIR 2000","artist":"ALBION","label":"PLATIPUS","peak":"59","WoC":"2"}]